cli/__init__.py
cli/main.py
cli/commands/__init__.py
cli/commands/appinfo.py
cli/commands/auth.py
cli/commands/download.py
cli/commands/purchase.py
cli/commands/search.py
cli/commands/version.py
cli/logger/__init__.py
cli/models/__init__.py
cli/models/account.py
networking/__init__.py
networking/http_client.py
store_api/__init__.py
store_api/common/__init__.py
store_api/common/storefront.py
store_api/itunes/__init__.py
store_api/itunes/itunes_client.py
store_api/itunes/itunes_endpoint.py
store_api/itunes/itunes_response.py
store_api/signature/__init__.py
store_api/signature/signature_client.py
store_api/store/__init__.py
store_api/store/store_client.py
store_api/store/store_endpoint.py
store_api/store/store_request.py
store_api/store/store_response.py
ipatoolpy-0.0.2.dist-info/METADATA
ipatoolpy-0.0.2.dist-info/WHEEL
ipatoolpy-0.0.2.dist-info/entry_points.txt
ipatoolpy-0.0.2.dist-info/top_level.txt
ipatoolpy-0.0.2.dist-info/RECORD
