Metadata-Version: 2.1
Name: ipatoolpy
Version: 0.0.2
Summary: ipatoolpy is a command line tool that allows you to search for iOS apps on the App Store and download a copy of the app package, known as an ipa file.
Home-page: https://github.com/1ookup/ipatoolpy
Author: 1ookup
Author-email: 1ookup@1ookup.1ookup
License: UNKNOWN
Platform: UNKNOWN
Requires-Python: >=3.5
Requires-Dist: setuptools
Requires-Dist: requests
Requires-Dist: click
Requires-Dist: loguru
Requires-Dist: psutil
Requires-Dist: PySocks
